estceque/__init__.py
estceque/builtin.py
estceque/core.py
estceque/frontend.py
estceque-0.5.dist-info/METADATA
estceque-0.5.dist-info/WHEEL
estceque-0.5.dist-info/RECORD
